rabbitmq_mcp_task_queue/__init__.py
rabbitmq_mcp_task_queue/py.typed
rabbitmq_mcp_task_queue/rabbitmq_task_queue.py
rabbitmq_mcp_task_queue-0.1.0.dist-info/METADATA
rabbitmq_mcp_task_queue-0.1.0.dist-info/WHEEL
rabbitmq_mcp_task_queue-0.1.0.dist-info/licenses/LICENSE
rabbitmq_mcp_task_queue-0.1.0.dist-info/RECORD
