Metadata-Version: 2.4
Name: rabbitmq-mcp-task-queue
Version: 0.1.0
Summary: RabbitMQ-based TaskMessageQueue implementation for MCP (Model Context Protocol)
Project-URL: Homepage, https://github.com/kenliao94/rabbitmq-mcp-task-queue
Project-URL: Repository, https://github.com/kenliao94/rabbitmq-mcp-task-queue
Project-URL: Issues, https://github.com/kenliao94/rabbitmq-mcp-task-queue/issues
Author-email: Your Name <your.email@example.com>
License: Apache-2.0
License-File: LICENSE
Keywords: async,mcp,model-context-protocol,rabbitmq,task-queue
Classifier: Development Status :: 4 - Beta
Classifier: Intended Audience :: Developers
Classifier: License :: OSI Approved :: Apache Software License
Classifier: Programming Language :: Python :: 3
Classifier: Programming Language :: Python :: 3.11
Classifier: Programming Language :: Python :: 3.12
Classifier: Topic :: Software Development :: Libraries :: Python Modules
Classifier: Topic :: System :: Distributed Computing
Requires-Python: >=3.11
Requires-Dist: anyio>=4.0.0
Requires-Dist: mcp>=1.25.0
Requires-Dist: pika>=1.3.0
